Workbook

Sheet Legende
A1: Classeur de calibrage — jeu spatial roguelite
A2: Version 5 — toutes stats sur 0-100, monnaie de run, coûts, fourchettes, critiques
A4: Onglets
A5: Statistiques | B5: Stats du vaisseau, valeurs initiales et paramètres de la formule.
A6: Evenements | B6: Une ligne par option : coût, gains, pertes, notes.
A7: Simulateur | B7: Résolution complète d'une option, avec critiques.
A9: Séquence de résolution d'une option
A10: 1. Coût | B10: Prélevé immédiatement, quel que soit le résultat.
A11: 2. Probabilité | B11: P_final = P_base + (Skill - 50) × 0,7, borné entre 5 % et 95 %.
A12: 3. Tirage | B12: Un jet d100. Réussite si jet ≤ P_final.
A13: 4. Critique | B13: Réussite critique si jet ≤ 5 + Skill × 0,10 (et ≤ P_final).
B14: Échec critique si jet > 100 − (15 − Skill × 0,10).
A15: 5. Effets | B15: Application des 1 ou 2 gains, ou des 1 ou 2 pertes.
A17: Règles d'effet
A18: Fourchette | B18: Un montant écrit 8000-12000 est tiré au hasard dans l'intervalle.
A19: Réussite critique | B19: Effets doublés. Sur une fourchette, on prend la borne haute.
A20: Échec critique | B20: Pertes doublées. Sur une fourchette, on prend la borne haute.
A21: Skills | B21: Peuvent monter et descendre. Le skill gagné ou perdu est celui qui gouverne l'option.
A22: Moral et Réputation | B22: Simples stats : ni condition de défaite, ni modulateur d'amplitude.
A24: Code couleur
A25: Fond jaune | B25: Cellule à remplir ou à ajuster.
A26: Fond vert | B26: Gains.
A27: Fond rouge | B27: Pertes.
A28: Fond gris | B28: Sans objet.

Sheet Statistiques
A1: Statistiques du vaisseau
A3: Statistique | B3: Famille | C3: Échelle | D3: Valeur initiale | E3: Rôle
A4: Carburant | B4: Physique | C4: 0-100 | D4: 100 | E4: Fin de run à zéro — dérive
A5: Coque | B5: Physique | C5: 0-100 | D5: 100 | E5: Fin de run à zéro — dislocation
A6: Moral | B6: Stat | C6: 0-100 | D6: 70 | E6: Simple stat, cible de gains et de pertes
A7: Réputation | B7: Stat | C7: 0-100 | D7: 50 | E7: Simple stat, cible de gains et de pertes
A8: Monnaie de Run | B8: Ressource | C8: ≥ 0 | D8: 2000 | E8: Dépensée pour les options payantes, perdue en fin de run
A9: Combat | B9: Skill | C9: 0-100 | D9: tiré | E9: Gouverne les options de combat
A10: Mécanique | B10: Skill | C10: 0-100 | D10: tiré | E10: Gouverne les options techniques
A11: Relationnel | B11: Skill | C11: 0-100 | D11: tiré | E11: Gouverne les options sociales
A12: Exploration | B12: Skill | C12: 0-100 | D12: tiré | E12: Gouverne les options de pilotage et de fouille
A14: Paramètres de la formule
A15: Point neutre (skills) | D15: 50 | E15: Ces valeurs pilotent tout l'équilibrage.
A16: Coefficient probabilité par point de skill | D16: 0.7
A17: Plancher de probabilité (%) | D17: 5
A18: Plafond de probabilité (%) | D18: 95
A19: Fenêtre de réussite critique — base (%) | D19: 5
A20: Fenêtre de réussite critique — bonus à skill 100 (%) | D20: 10
A21: Fenêtre d'échec critique — base à skill 0 (%) | D21: 15
A22: Multiplicateur critique | D22: 2
A24: Génération des skills au départ
A25: Budget total à répartir sur 4 skills | D25: 200
A26: Valeur minimale par skill | D26: 20
A27: Valeur maximale par skill | D27: 80
A29: Bornes de P_base recommandées
A30: Option sécurisée (%) | D30: 85 | E30: L'option sécurisée garantit une issue à tout profil, même sans le bon skill.
A31: Option facile (%) | D31: 60
A32: Option moyenne (%) | D32: 45
A33: Revenus récurrents | D33: 30
A34: Solde versée par la station commanditaire (par chapitre) | D34: 5000 | E34: Créditée automatiquement à l'ouverture de chaque chapitre.

Sheet Evenements
A1: Calibrage des options
A2: Coût prélevé quoi qu'il arrive. Les fourchettes sont tirées au hasard. Un critique double les effets.
A4: Catégorie | B4: Événement | C4: Option | D4: Type | E4: Skill gouvernant | F4: P_base (%) | G4: Cout_stat | H4: CoutNb | I4: Win_Stat1 | J4: GainStat1 | K4: Win_Stat2 | L4: GainStat2 | M4: Lose_Stat1 | N4: PerteStat1 | O4: Lose_Stat2 | P4: PerteStat2 | Q4: Notes
A5: Ressources | B5: Champ d'astéroïdes | C5: Contourner | D5: Aléatoire | E5: Exploration | F5: 85 | G5: Carburant | H5: 15 | M5: Moral | N5: 8 | Q5: Aucun gain : le gain est de ne pas endommager le vaisseau. Le carburant est perdu quoi qu'il arrive. En cas d'échec, le vaisseau s'égare et l'équipage perd le moral.
A6: Ressources | B6: Champ d'astéroïdes | C6: Foncer | D6: Aléatoire | E6: Exploration | F6: 40 | I6: Moral | J6: 2 | K6: Exploration | L6: 8 | M6: Moral | N6: 2 | O6: Coque | P6: 17
A7: Ressources | B7: Épave dérivante | C7: Démonter les pièces | D7: Aléatoire | E7: Mécanique | F7: 50 | I7: Monnaie de Run | J7: 7000-12000 | K7: Mécanique | L7: 5 | M7: Mécanique | N7: 5 | Q7: Principale source de revenus du run.
A8: Ressources | B8: Épave dérivante | C8: Fouiller les registres | D8: Aléatoire | E8: Exploration | F8: 50 | I8: Monnaie de Run | J8: 1000-3000 | K8: Exploration | L8: 10 | M8: Coque | N8: 10 | Q8: En cas d'échec, la fouille déclenche accidentellement l'autodestruction de l'épave : le vaisseau encaisse des dégâts.
A9: Ressources | B9: Épave dérivante | C9: Ignorer | D9: Déterministe | E9: —
A10: Ressources | B10: Fuite mineure | C10: Réparer proprement | D10: Aléatoire | E10: Mécanique | F10: 85 | G10: Monnaie de Run | H10: 4000 | I10: Coque | J10: 12 | K10: Mécanique | L10: 8 | M10: Coque | N10: 5
A11: Ressources | B11: Fuite mineure | C11: Colmater vite fait | D11: Aléatoire | E11: Mécanique | F11: 55 | G11: Monnaie de Run | H11: 2500 | I11: Coque | J11: 9 | M11: Coque | N11: 7 | O11: Mécanique | P11: 8
A12: Ressources | B12: Station de ravitaillement | C12: Négocier le plein | D12: Aléatoire | E12: Relationnel | F12: 50 | G12: Monnaie de Run | H12: 2000 | I12: Carburant | J12: 50
A13: Ressources | B13: Station de ravitaillement | C13: Passer | D13: Déterministe | E13: —
A14: Combat | B14: Patrouille pirate | C14: Combattre | D14: Aléatoire | E14: Combat | F14: 40 | I14: Réputation | J14: 15 | K14: Combat | L14: 10 | M14: Réputation | N14: 15 | O14: Coque | P14: 20
A15: Combat | B15: Patrouille pirate | C15: Payer un péage | D15: Aléatoire | E15: Relationnel | F15: 45 | G15: Monnaie de Run | H15: 10000 | I15: Relationnel | J15: 15 | M15: Monnaie de Run | N15: 7500 | Q15: En cas d'échec, les pillards extorquent de l'argent supplémentaire puis laissent passer.
A16: Combat | B16: Patrouille pirate | C16: Fuir | D16: Aléatoire | E16: Exploration | F16: 60 | G16: Carburant | H16: 12 | M16: Monnaie de Run | N16: 7500
A17: Combat | B17: Créature accrochée à la coque | C17: Repousser | D17: Aléatoire | E17: Combat | F17: 50 | I17: Combat | J17: 8 | M17: Coque | N17: 15 | Q17: En cas d'échec, la créature finit par lâcher en emportant un morceau de coque.
A18: Combat | B18: Créature accrochée à la coque | C18: Manœuvre brusque | D18: Aléatoire | E18: Exploration | F18: 30 | G18: Carburant | H18: 5 | M18: Coque | N18: 20 | Q18: En cas d'échec, la créature finit par lâcher en emportant un morceau de coque.
A19: Combat | B19: Drone de guerre autonome | C19: Détruire | D19: Aléatoire | E19: Combat | F19: 50 | I19: Monnaie de Run | J19: 8000-12000 | K19: Combat | L19: 10 | M19: Coque | N19: 20 | Q19: En cas d'échec, la patrouille propriétaire du drone arrive et se venge : 20 points de dégâts à la coque.
A20: Combat | B20: Drone de guerre autonome | C20: Brouiller ses capteurs | D20: Aléatoire | E20: Mécanique | F20: 50 | I20: Mécanique | J20: 12 | K20: Moral | L20: 8 | M20: Monnaie de Run | N20: 2500 | Q20: En cas d'échec, le brouilleur casse, ce qui coûte de l'argent.
A21: Équipage | B21: Dispute à bord | C21: Trancher fermement | D21: Aléatoire | E21: Relationnel | F21: 50 | I21: Moral | J21: 25 | M21: Moral | N21: 25
A22: Équipage | B22: Dispute à bord | C22: Laisser faire | D22: Aléatoire | E22: Relationnel | F22: 75 | I22: Moral | J22: 10 | M22: Moral | N22: 35
A23: Équipage | B23: Fatigue accumulée | C23: Repos forcé | D23: Déterministe | E23: — | G23: Carburant | H23: 10 | I23: Moral | J23: 10 | Q23: Coûte du carburant car le vaisseau erre sans action spécifique. Aucune défaite possible.
A24: Équipage | B24: Fatigue accumulée | C24: Continuer | D24: Aléatoire | E24: Relationnel | F24: 40 | I24: Relationnel | J24: 15 | K24: Moral | L24: 8 | M24: Moral | N24: 15 | Q24: En cas de réussite, l'effort commun renforce la cohésion et fait monter le moral.
A25: Réputation | B25: Signal de détresse | C25: Porter secours | D25: Aléatoire | E25: Relationnel | F25: 50 | G25: Carburant | H25: 5 | I25: Réputation | J25: 17 | K25: Relationnel | L25: 12 | M25: Monnaie de Run | N25: 2500 | O25: Carburant | P25: 15 | Q25: En cas d'échec, il s'agissait de pirates qui faisaient semblant : ils prennent argent et carburant.
A26: Réputation | B26: Signal de détresse | C26: Réparer leur vaisseau | D26: Aléatoire | E26: Mécanique | F26: 40 | G26: Monnaie de Run | H26: 2000 | I26: Monnaie de Run | J26: 10000 | K26: Réputation | L26: 20 | M26: Coque | N26: 12 | O26: Réputation | P26: 18 | Q26: En cas d'échec, le vaisseau secouru explose pendant la manipulation : dégâts au vaisseau et réputation entachée.
A27: Réputation | B27: Signal de détresse | C27: Ignorer | D27: Déterministe | E27: — | G27: Réputation | H27: 7 | Q27: Ignorer un appel fait légèrement baisser la réputation.
A28: Réputation | B28: Marché contrebandiers | C28: Négocier | D28: Aléatoire | E28: Relationnel | F28: 40 | G28: Monnaie de Run | H28: 2500 | I28: Monnaie de Run | J28: 2000-15000 | K28: Relationnel | L28: 12 | M28: Monnaie de Run | N28: 1000-2500 | O28: Carburant | P28: 15 | Q28: En cas d'échec, les contrebandiers prennent davantage d'argent et un peu de carburant.
A29: Réputation | B29: Marché contrebandiers | C29: Refuser | D29: Aléatoire | E29: Exploration | F29: 85 | M29: Monnaie de Run | N29: 1000-2500 | O29: Carburant | P29: 10 | Q29: En cas d'échec, les contrebandiers rattrapent le vaisseau pendant la fuite et le pillent.
A31: Règle : le skill gagné ou perdu par une option est toujours celui qui la gouverne.
A32: Règle : chaque événement propose au moins une issue viable pour un profil qui n'a pas le bon skill.

Sheet Simulateur
A1: Simulateur de résolution
A3: Entrées
A4: P_base de l'option (%) | B4: 50
A5: Skill gouvernant (0-100) | B5: 70
A6: Gain — borne basse | B6: 8000
A7: Gain — borne haute | B7: 12000
A8: Perte de base | B8: 20
A10: Résultats
A11: P_final borné (%) | B11: =MIN(Statistiques!$D$18,MAX(Statistiques!$D$17,B4+(B5-Statistiques!$D$15)*Statistiques!$D$16)) -> 64
A12: Fenêtre de réussite critique (%) | B12: =MIN(B11,Statistiques!$D$19+B5*Statistiques!$D$20/100) -> 12
A13: Fenêtre d'échec critique (%) | B13: =Statistiques!$D$21-B5*Statistiques!$D$20/100 -> 8
A14: Gain moyen (hors critique) | B14: =(B6+B7)/2 -> 10000
A15: Gain en réussite critique | B15: =B7*Statistiques!$D$22 -> 24000
A16: Perte en échec critique | B16: =B8*Statistiques!$D$22 -> 40
A19: Courbe de probabilité selon le skill
A20: Skill | B20: P_final (%) | C20: Crit. réussite (%) | D20: Crit. échec (%)
A21: 0 | B21: =MIN(Statistiques!$D$18,MAX(Statistiques!$D$17,$B$4+(A21-Statistiques!$D$15)*Statistiques!$D$16)) -> 15 | C21: =MIN(B21,Statistiques!$D$19+A21*Statistiques!$D$20/100) -> 5 | D21: =Statistiques!$D$21-A21*Statistiques!$D$20/100 -> 15
A22: 10 | B22: =MIN(Statistiques!$D$18,MAX(Statistiques!$D$17,$B$4+(A22-Statistiques!$D$15)*Statistiques!$D$16)) -> 22 | C22: =MIN(B22,Statistiques!$D$19+A22*Statistiques!$D$20/100) -> 6 | D22: =Statistiques!$D$21-A22*Statistiques!$D$20/100 -> 14
A23: 20 | B23: =MIN(Statistiques!$D$18,MAX(Statistiques!$D$17,$B$4+(A23-Statistiques!$D$15)*Statistiques!$D$16)) -> 29 | C23: =MIN(B23,Statistiques!$D$19+A23*Statistiques!$D$20/100) -> 7 | D23: =Statistiques!$D$21-A23*Statistiques!$D$20/100 -> 13
A24: 30 | B24: =MIN(Statistiques!$D$18,MAX(Statistiques!$D$17,$B$4+(A24-Statistiques!$D$15)*Statistiques!$D$16)) -> 36 | C24: =MIN(B24,Statistiques!$D$19+A24*Statistiques!$D$20/100) -> 8 | D24: =Statistiques!$D$21-A24*Statistiques!$D$20/100 -> 12
A25: 40 | B25: =MIN(Statistiques!$D$18,MAX(Statistiques!$D$17,$B$4+(A25-Statistiques!$D$15)*Statistiques!$D$16)) -> 43 | C25: =MIN(B25,Statistiques!$D$19+A25*Statistiques!$D$20/100) -> 9 | D25: =Statistiques!$D$21-A25*Statistiques!$D$20/100 -> 11
A26: 50 | B26: =MIN(Statistiques!$D$18,MAX(Statistiques!$D$17,$B$4+(A26-Statistiques!$D$15)*Statistiques!$D$16)) -> 50 | C26: =MIN(B26,Statistiques!$D$19+A26*Statistiques!$D$20/100) -> 10 | D26: =Statistiques!$D$21-A26*Statistiques!$D$20/100 -> 10
A27: 60 | B27: =MIN(Statistiques!$D$18,MAX(Statistiques!$D$17,$B$4+(A27-Statistiques!$D$15)*Statistiques!$D$16)) -> 57 | C27: =MIN(B27,Statistiques!$D$19+A27*Statistiques!$D$20/100) -> 11 | D27: =Statistiques!$D$21-A27*Statistiques!$D$20/100 -> 9
A28: 70 | B28: =MIN(Statistiques!$D$18,MAX(Statistiques!$D$17,$B$4+(A28-Statistiques!$D$15)*Statistiques!$D$16)) -> 64 | C28: =MIN(B28,Statistiques!$D$19+A28*Statistiques!$D$20/100) -> 12 | D28: =Statistiques!$D$21-A28*Statistiques!$D$20/100 -> 8
A29: 80 | B29: =MIN(Statistiques!$D$18,MAX(Statistiques!$D$17,$B$4+(A29-Statistiques!$D$15)*Statistiques!$D$16)) -> 71 | C29: =MIN(B29,Statistiques!$D$19+A29*Statistiques!$D$20/100) -> 13 | D29: =Statistiques!$D$21-A29*Statistiques!$D$20/100 -> 7
A30: 90 | B30: =MIN(Statistiques!$D$18,MAX(Statistiques!$D$17,$B$4+(A30-Statistiques!$D$15)*Statistiques!$D$16)) -> 78 | C30: =MIN(B30,Statistiques!$D$19+A30*Statistiques!$D$20/100) -> 14 | D30: =Statistiques!$D$21-A30*Statistiques!$D$20/100 -> 6
A31: 100 | B31: =MIN(Statistiques!$D$18,MAX(Statistiques!$D$17,$B$4+(A31-Statistiques!$D$15)*Statistiques!$D$16)) -> 85 | C31: =MIN(B31,Statistiques!$D$19+A31*Statistiques!$D$20/100) -> 15 | D31: =Statistiques!$D$21-A31*Statistiques!$D$20/100 -> 5

Sheet Planetes
A1: Calibrage — événement planète
A3: Choix à la détection
A4: Choix | B4: Effet | C4: Comptée au score
A5: Explorer | B5: Tire le type de planète (table ci-dessous) | C5: Oui | D5: Gain du scan (fixe)
A6: Scanner à distance | B6: 150 | C6: Oui
A7: Ignorer | B7: Aucun effet | C7: Non
A9: Table des types de planète (tirage à l'exploration)
A10: Type | B10: Probabilité (%) | C10: Gain run — bas | D10: Gain run — haut | E10: Monnaie persistante | F10: Trophée | G10: Effet additionnel
A11: Classique | B11: 50 | C11: 2000 | D11: 5000 | E11: 0 | F11: Non
A12: Anomalie | B12: 10 | C12: 15000 | D12: 20000 | E12: à calibrer | F12: Oui | G12: Ajoute un trophée unique au portefeuille
A13: Paradisiaque | B13: 20 | C13: 0 | D13: 0 | E13: 0,01% de la monnaie de run si arrêt | F13: Non | G13: Permet de terminer le run en victoire
A14: Infernale | B14: 20 | C14: 0 | D14: 0 | E14: 0 | F14: Non | G14: Coque ramenée à 10% (ou explosion si déjà ≤10%) ; -50% monnaie de run
A15: Somme des probabilités | B15: =SUM(B11:B14) -> 100
A18: Caractéristiques combinables (tirage indépendant, pondération à définir)
A19: Climat | B19: Terrain | C19: Atmosphère | D19: Système stellaire | E19: Écosystème
A20: Infernal | B20: Eau | C20: Inexistante | D20: Errante | E20: Pas de vie
A21: Chaud | B21: Jungle | C21: Toxique | D21: 1 soleil | E21: Vie primitive
A22: Tempéré | B22: Désert rocailleux | C22: Irrespirable | D22: 2 soleils | E22: Vie animale
A23: Froid | B23: Désert glacé | C23: Respirable | D23: 3 soleils | E23: Vie intelligente
A24: Glacial | B24: Gaz | C24: Dense | D24: Trou noir | E24: Société complexe établie
D25: Étoile à neutrons
A28: Poids de rareté (%) à définir par valeur, doit sommer à 100 par colonne
A31: Génération du nom : [Préfixe Système] + [Racine] + [Suffixe Climat]
A32: Système stellaire | B32: Préfixe | C32: Climat | D32: Suffixe
A33: Errante | B33: Kesh- | C33: Infernal | D33: -agon
A34: 1 soleil | B34: Sol- | C34: Chaud | D34: -ora
A35: 2 soleils | B35: Bi- | C35: Tempéré | D35: -eth
A36: 3 soleils | B36: Tri- | C36: Froid | D36: -ice
A37: Trou noir | B37: Abys- | C37: Glacial | D37: -friz
A38: Étoile à neutrons | B38: Puls-
A40: Banque de racines (à compléter)
A41: tara | B41: mund | C41: oth | D41: vex | E41: illia | F41: kar | G41: nyx
